README.md
setup.cfg
setup.py
napalm_ros_di_di/__init__.py
napalm_ros_di_di/query.py
napalm_ros_di_di/ros.py
napalm_ros_di_di/utils.py
napalm_ros_di_di.egg-info/PKG-INFO
napalm_ros_di_di.egg-info/SOURCES.txt
napalm_ros_di_di.egg-info/dependency_links.txt
napalm_ros_di_di.egg-info/requires.txt
napalm_ros_di_di.egg-info/top_level.txt