Metadata-Version: 2.1
Name: napalm-ros-di-di
Version: 0.13
Summary: driver napalm functionality for mikrotik devices
Home-page: UNKNOWN
Author: Ilya Gulin
License: Apache 2.0
Platform: UNKNOWN
